Gooayeproject/__init__.py
Gooayeproject/items.py
Gooayeproject/middlewares.py
Gooayeproject/pipelines.py
Gooayeproject/settings.py
Gooayeproject/spiders/__init__.py
Gooayeproject/spiders/gooaye.py
scrapy_gooaye-0.0.2.dist-info/LICENSE.txt
scrapy_gooaye-0.0.2.dist-info/METADATA
scrapy_gooaye-0.0.2.dist-info/WHEEL
scrapy_gooaye-0.0.2.dist-info/top_level.txt
scrapy_gooaye-0.0.2.dist-info/RECORD
