Metadata-Version: 2.1
Name: scrapy-gooaye
Version: 0.0.2
Summary: Scrapy spider for Gooaye Website
Home-page: https://github.com/Bluesss30/Gooaye
Author: Blue
Author-email: iamjasonlan@gmail.com
License: UNKNOWN
Platform: UNKNOWN
Classifier: Programming Language :: Python :: 3
Classifier: License :: OSI Approved :: MIT License
Classifier: Operating System :: OS Independent
Requires-Python: >=3.6
License-File: LICENSE.txt
Requires-Dist: Scrapy (>=1)
